{
  "en": {
    "app_title": "OptiWindows - Ultimate Windows Optimizer",
    "nav": {
      "dashboard": "Dashboard",
      "cleaner": "Cleaner",
      "optimizer": "Optimizer",
      "privacy": "Privacy",
      "gaming": "Gaming",
      "disk": "Disk Manager",
      "startup": "Startup",
      "apps": "Apps Installer",
      "tweaks": "Tweaks",
      "repair": "Repair",
      "features": "Features",
      "monitoring": "Monitoring",
      "settings": "Settings"
    },
    "dashboard": {
      "welcome": "Welcome to OptiWindows",
      "system_info": "System Information",
      "cpu": "CPU",
      "ram": "RAM",
      "disk": "Disk",
      "os": "Operating System",
      "health_score": "System Health",
      "quick_actions": "Quick Actions",
      "clean_now": "Clean Now",
      "optimize_now": "Optimize Now",
      "check_health": "Check Health",
      "loading": "Loading system information..."
    },
    "cleaner": {
      "title": "System Cleaner",
      "select_all": "Select All",
      "deselect_all": "Deselect All",
      "start_cleaning": "Start Cleaning",
      "scanning": "Scanning...",
      "temp_files": "Temporary Files",
      "recycle_bin": "Recycle Bin",
      "browser_cache": "Browser Cache",
      "windows_update": "Windows Update Cache",
      "thumbnails": "Thumbnail Cache",
      "delivery_opt": "Delivery Optimization",
      "log_files": "Log Files",
      "crash_dumps": "Crash Dumps",
      "windows_old": "Windows.old Folder",
      "defender_logs": "Windows Defender Logs"
    },
    "optimizer": {
      "title": "System Optimizer",
      "performance": "Performance Optimizations",
      "visual": "Visual Effects",
      "advanced": "Advanced Tweaks",
      "disable_telemetry": "Disable Windows Telemetry",
      "optimize_memory": "Optimize Memory Management",
      "disable_bg_apps": "Disable Background Apps",
      "optimize_cpu": "Optimize Processor Scheduling",
      "disable_superfetch": "Disable Superfetch/Prefetch",
      "optimize_network": "Optimize Network Settings",
      "disable_search": "Disable Search Indexing",
      "animations": "Disable Animations",
      "transparency": "Disable Transparency",
      "shadows": "Disable Shadows",
      "hibernation": "Disable Hibernation",
      "system_restore": "Disable System Restore",
      "page_file": "Disable Page File",
      "optimize_ssd": "Optimize SSD (TRIM)"
    },
    "privacy": {
      "title": "Privacy & Security",
      "tracking": "Disable Activity Tracking",
      "location": "Disable Location Services",
      "camera": "Disable Camera Access",
      "microphone": "Disable Microphone Access",
      "diagnostics": "Disable Diagnostic Data",
      "advertising": "Disable Advertising ID",
      "wifi_sense": "Disable WiFi Sense",
      "web_search": "Disable Web Search in Start Menu"
    },
    "gaming": {
      "title": "Gaming Optimizations",
      "mode": "Enable Game Mode",
      "dvr": "Disable Game DVR",
      "fullscreen": "Optimize Fullscreen Mode",
      "mouse": "Reduce Mouse Lag",
      "gpu": "Optimize GPU Settings",
      "power": "High Performance Power Plan"
    },
    "repair": {
      "title": "System Repair Tools",
      "sfc": "System File Checker",
      "dism": "DISM Repair",
      "disk_check": "Disk Check",
      "network_reset": "Network Reset",
      "windows_update": "Windows Update Repair",
      "registry": "Registry Repair"
    },
    "settings": {
      "title": "Settings",
      "general": "General Settings",
      "language": "Language",
      "theme": "Theme",
      "dark": "Dark",
      "light": "Light",
      "system": "System",
      "auto_backup": "Automatic Backup Before Changes",
      "show_warnings": "Show Warning Messages",
      "advanced_mode": "Advanced Mode",
      "telemetry": "Send Anonymous Telemetry",
      "auto_update": "Automatic Update Check",
      "optimization": "Optimization Settings",
      "restore_point": "Create Restore Point Before Optimization",
      "aggressive": "Aggressive Cleaning Mode",
      "deep_scan": "Deep Scan",
      "scheduled": "Scheduled Tasks",
      "enable_scheduled": "Enable Scheduled Tasks",
      "frequency": "Frequency",
      "daily": "Daily",
      "weekly": "Weekly",
      "monthly": "Monthly",
      "day": "Day",
      "time": "Time",
      "about": "About",
      "version": "Version",
      "check_update": "Check for Updates",
      "github": "View on GitHub",
      "save": "Save Settings",
      "reset": "Reset to Defaults",
      "export": "Export Configuration",
      "import": "Import Configuration"
    },
    "common": {
      "success": "Success",
      "error": "Error",
      "warning": "Warning",
      "cancel": "Cancel",
      "ok": "OK",
      "yes": "Yes",
      "no": "No",
      "apply": "Apply",
      "close": "Close",
      "admin_required": "Administrator Required",
      "admin_msg": "Administrator privileges are required for this operation."
    }
  },
  "fr": {
    "app_title": "OptiWindows - Optimiseur Windows Ultime",
    "nav": {
      "dashboard": "Tableau de bord",
      "cleaner": "Nettoyeur",
      "optimizer": "Optimiseur",
      "privacy": "Confidentialité",
      "gaming": "Gaming",
      "disk": "Gestionnaire Disque",
      "startup": "Démarrage",
      "apps": "Installateur Apps",
      "tweaks": "Ajustements",
      "repair": "Réparation",
      "features": "Fonctionnalités",
      "monitoring": "Surveillance",
      "settings": "Paramètres"
    },
    "dashboard": {
      "welcome": "Bienvenue sur OptiWindows",
      "system_info": "Informations Système",
      "cpu": "Processeur",
      "ram": "Mémoire RAM",
      "disk": "Disque",
      "os": "Système d'exploitation",
      "health_score": "État du Système",
      "quick_actions": "Actions Rapides",
      "clean_now": "Nettoyer",
      "optimize_now": "Optimiser",
      "check_health": "Vérifier l'État",
      "loading": "Chargement des informations système..."
    },
    "cleaner": {
      "title": "Nettoyeur Système",
      "select_all": "Tout Sélectionner",
      "deselect_all": "Tout Désélectionner",
      "start_cleaning": "Lancer le Nettoyage",
      "scanning": "Analyse en cours...",
      "temp_files": "Fichiers Temporaires",
      "recycle_bin": "Corbeille",
      "browser_cache": "Cache Navigateur",
      "windows_update": "Cache Windows Update",
      "thumbnails": "Cache Miniatures",
      "delivery_opt": "Optimisation de Distribution",
      "log_files": "Fichiers Journaux",
      "crash_dumps": "Rapports de Crash",
      "windows_old": "Dossier Windows.old",
      "defender_logs": "Journaux Windows Defender"
    },
    "optimizer": {
      "title": "Optimiseur Système",
      "performance": "Optimisations Performance",
      "visual": "Effets Visuels",
      "advanced": "Ajustements Avancés",
      "disable_telemetry": "Désactiver la Télémétrie Windows",
      "optimize_memory": "Optimiser la Gestion Mémoire",
      "disable_bg_apps": "Désactiver les Apps en Arrière-plan",
      "optimize_cpu": "Optimiser la Planification Processeur",
      "disable_superfetch": "Désactiver Superfetch/Prefetch",
      "optimize_network": "Optimiser les Paramètres Réseau",
      "disable_search": "Désactiver l'Indexation",
      "animations": "Désactiver les Animations",
      "transparency": "Désactiver la Transparence",
      "shadows": "Désactiver les Ombres",
      "hibernation": "Désactiver l'Hibernation",
      "system_restore": "Désactiver la Restauration Système",
      "page_file": "Désactiver le Fichier d'Échange",
      "optimize_ssd": "Optimiser SSD (TRIM)"
    },
    "privacy": {
      "title": "Confidentialité & Sécurité",
      "tracking": "Désactiver le Suivi d'Activité",
      "location": "Désactiver les Services de Localisation",
      "camera": "Désactiver l'Accès Caméra",
      "microphone": "Désactiver l'Accès Microphone",
      "diagnostics": "Désactiver les Données Diagnostiques",
      "advertising": "Désactiver l'ID Publicitaire",
      "wifi_sense": "Désactiver WiFi Sense",
      "web_search": "Désactiver Recherche Web dans Menu Démarrer"
    },
    "gaming": {
      "title": "Optimisations Gaming",
      "mode": "Activer le Mode Jeu",
      "dvr": "Désactiver Game DVR",
      "fullscreen": "Optimiser Mode Plein Écran",
      "mouse": "Réduire le Lag Souris",
      "gpu": "Optimiser les Paramètres GPU",
      "power": "Plan d'Alimentation Performances"
    },
    "repair": {
      "title": "Outils de Réparation",
      "sfc": "Vérificateur Fichiers Système",
      "dism": "Réparation DISM",
      "disk_check": "Vérification Disque",
      "network_reset": "Réinitialisation Réseau",
      "windows_update": "Réparation Windows Update",
      "registry": "Réparation Registre"
    },
    "settings": {
      "title": "Paramètres",
      "general": "Paramètres Généraux",
      "language": "Langue",
      "theme": "Thème",
      "dark": "Sombre",
      "light": "Clair",
      "system": "Système",
      "auto_backup": "Sauvegarde Automatique Avant Modifications",
      "show_warnings": "Afficher les Messages d'Avertissement",
      "advanced_mode": "Mode Avancé",
      "telemetry": "Envoyer Télémétrie Anonyme",
      "auto_update": "Vérification Automatique des Mises à Jour",
      "optimization": "Paramètres d'Optimisation",
      "restore_point": "Créer Point de Restauration Avant Optimisation",
      "aggressive": "Mode Nettoyage Agressif",
      "deep_scan": "Analyse Approfondie",
      "scheduled": "Tâches Planifiées",
      "enable_scheduled": "Activer les Tâches Planifiées",
      "frequency": "Fréquence",
      "daily": "Quotidien",
      "weekly": "Hebdomadaire",
      "monthly": "Mensuel",
      "day": "Jour",
      "time": "Heure",
      "about": "À Propos",
      "version": "Version",
      "check_update": "Vérifier les Mises à Jour",
      "github": "Voir sur GitHub",
      "save": "Enregistrer",
      "reset": "Réinitialiser",
      "export": "Exporter Configuration",
      "import": "Importer Configuration"
    },
    "common": {
      "success": "Succès",
      "error": "Erreur",
      "warning": "Avertissement",
      "cancel": "Annuler",
      "ok": "OK",
      "yes": "Oui",
      "no": "Non",
      "apply": "Appliquer",
      "close": "Fermer",
      "admin_required": "Administrateur Requis",
      "admin_msg": "Les privilèges administrateur sont requis pour cette opération."
    }
  }
}
